UFMG_CienciaDaComputacao/2023_2/IntroducaoAosSistemasLogicos/TP_ISL_Lucas_Santos/Decifrador_Lucas_Santos/design.sv
// Módulo para a porta XOR implementada no estilo estrutural
module xor_gate(a, b, out);
 input a, b;
 output out;
 wire a_bar, b_bar, x, y;
 
 // Complemento (inverso) das entradas
 not a_inv (a_bar, a);
 not b_inv (b_bar, b);
 
 // AND gates para a implementação da XOR
 and a1 (x, a_bar, b);
 and a2 (y, a, b_bar);
 
 // OR gate para a saída da XOR
 or or1 (out, x, y);
endmodule

// Módulo do Flip-Flop D
module d_flip_flop (
 input wire clk,
 input wire rst,
 input wire d,
 output reg q
);

 always @(posedge clk or posedge rst) begin
   if (rst) begin
     q <= 1'b0; // Reseta o flip-flop
   end else begin
     q <= d;    // Atualiza o flip-flop com os dados de entrada
   end
 end

endmodule

// Módulo do Registrador de Deslocamento
module shift_register #(parameter WIDTH = 32)(
 input wire clk,
 input wire rst,
 input wire [WIDTH-1:0] data_in,
 input wire shift_enable,
 output reg [WIDTH-1:0] data_out
);

 always @(posedge clk or posedge rst) begin
   if (rst) begin
     data_out <= {WIDTH{1'b0}}; // Reseta o registrador de deslocamento
   end else begin
     if (shift_enable) begin
       data_out <= {data_in[WIDTH-1], data_out[WIDTH-1:1]}; // Desloca os dados
     end
   end
 end

endmodule

// Módulo do Cifrador de Fluxo
module stream_cipher #(parameter BITS = 64)(
 input wire clk,
 input wire rst,
 input wire [BITS-1:0] message,
 input wire [BITS/2-1:0] otp,
 output reg [BITS-1:0] ciphered_message
);

 wire [BITS-1:0] shift_register_out;

 // Instanciação do registrador de deslocamento
 shift_register #(BITS) sr (
   .clk(clk),
   .rst(rst),
   .data_in(message),
   .shift_enable(1'b1),
   .data_out(shift_register_out)
 );

 // Operação XOR para criptografia
 always @(posedge clk or posedge rst) begin
   if (rst) begin
     ciphered_message <= 0; // Reseta a mensagem cifrada
   end else begin
     // Atualiza a mensagem cifrada usando a saída do registrador de deslocamento e o OTP
     ciphered_message <= shift_register_out ^ {otp, {BITS/2{1'b0}}};
   end
 end

endmodule

UFMG_CienciaDaComputacao/2023_2/IntroducaoAosSistemasLogicos/TP_ISL_Lucas_Santos/Decifrador_Lucas_Santos/testbench.sv
// Módulo de teste para o decifrador
module decifra #(parameter BITS = 64);
 // Mensagem cifrada de entrada
  reg [BITS-1:0] in = 64'b00000011_00011010_00000010_00010111_00000011_00000101_00010111_00010110;
 // Registrador de tamanho 32, contendo o OTP
 reg [BITS/2-1:0] otp = 32'b01100110_01101001_01110110_01100101;
 // Registradores e fios auxiliares, para decifrar a mensagem bit-a-bit.
 // A saída precisa ser um fio, pois a porta XOR precisa produzir seu sinal
 // em um meio que permita atribuição contínua.
 reg a, b;
 wire out;
 // Instanciação da porta XOR
 xor_gate xorg(.a(a), .b(b), .out(out));

 // Inicialização do arquivo VCD para simulação
 initial begin
   $dumpfile("dump_decifra.vcd");
   $dumpvars(1, a, b, out);
 end

 // Contador do loop for
 integer i;
 integer bits_per_group = 8; // Número de bits por grupo
 integer bits_counter = 0;  // Contador de bits no grupo

 // Inicialização do loop for para decifrar a mensagem bit-a-bit
 initial begin
   for(i = BITS-1; i >= 0; i = i - 1) begin
     a = in[i];
     b = (i >= BITS/2) ? otp[i-BITS/2] : otp[i];
     #1
     // Exibe o bit atual
     $write(out);

     // Contagem de bits no grupo
     bits_counter = bits_counter + 1;

     // Adiciona espaço entre grupos
     if (bits_counter == bits_per_group) begin
       $write(" ");
       bits_counter = 0;
     end
   end

   // Adiciona uma quebra de linha no final
   $write("\n");
 end
endmodule

UFMG_CienciaDaComputacao/2023_2/IntroducaoAosSistemasLogicos/TP_ISL_Lucas_Santos/Decifrador_Lucas_Santos/dump_decifra.vcd
$date
	Mon Dec 11 22:22:25 2023
$end
$version
	Icarus Verilog
$end
$timescale
	1s
$end
$scope module decifra $end
$var reg 1 ! a $end
$upscope $end
$scope module decifra $end
$var reg 1 " b $end
$upscope $end
$scope module decifra $end
$var wire 1 # out $end
$upscope $end
$enddefinitions $end
#0
$dumpvars
0#
0"
0!
$end
#1
1#
1"
#3
0#
0"
#5
1#
1"
#6
0#
1!
#7
1#
0"
#8
0#
0!
#9
1#
1"
#11
1#
0"
1!
#12
0#
1"
#13
0"
0!
#14
1#
1!
#15
1"
0!
#16
0#
0"
#17
1#
1"
#20
0#
0"
#21
1#
1"
#22
0#
1!
#23
0"
0!
#25
1#
1"
#27
1#
0"
1!
#28
0#
0!
#29
0#
1"
1!
#30
1#
0"
#31
0#
1"
#32
0"
0!
#33
1#
1"
#35
0#
0"
#37
1#
1"
#38
0#
1!
#39
1#
0"
#40
0#
0!
#41
1#
1"
#43
0#
0"
#44
1#
1"
#45
1#
0"
1!
#46
0#
0!
#47
0#
1"
1!
#48
0"
0!
#49
1#
1"
#51
0#
1!
#52
0"
0!
#53
0#
1"
1!
#55
1#
0"
#56
0#
0!
#57
1#
1"
#59
1#
0"
1!
#60
0#
0!
#61
0#
1"
1!
#62
1#
0"
#63
1"
0!
